ragchunker/__init__.py
ragchunker/chunking.py
ragchunker/embeddings.py
ragchunker/file_ingestion.py
ragchunker/provenance.py
ragchunker/rag_pipeline.py
ragchunker/storage.py
ragchunker-0.1.4.dist-info/licenses/LICENSE
ragchunker-0.1.4.dist-info/METADATA
ragchunker-0.1.4.dist-info/WHEEL
ragchunker-0.1.4.dist-info/top_level.txt
ragchunker-0.1.4.dist-info/RECORD
