Metadata-Version: 2.4
Name: ragchunker
Version: 0.1.4
Summary: A lightweight RAG chunking and preprocessing library
Author-email: Muhammad Usama <muhammadusama7207@gmail.com>
License: MIT
Classifier: Programming Language :: Python :: 3
Classifier: License :: OSI Approved :: MIT License
Classifier: Operating System :: OS Independent
Requires-Python: >=3.8
License-File: LICENSE
Requires-Dist: pdfminer.six==20250506
Requires-Dist: python-docx==1.2.0
Requires-Dist: python-pptx==1.0.2
Requires-Dist: pillow==11.3.0
Requires-Dist: pytesseract==0.3.13
Requires-Dist: openai-whisper==20250625
Requires-Dist: pandas==2.3.3
Requires-Dist: pyarrow==21.0.0
Requires-Dist: beautifulsoup4==4.14.2
Requires-Dist: trafilatura==2.0.0
Requires-Dist: nltk==3.9.2
Requires-Dist: scikit-learn==1.7.2
Requires-Dist: sentence-transformers==5.1.1
Requires-Dist: numpy==2.3.3
Requires-Dist: hf_xet==1.1.10
Requires-Dist: openai==2.3.0
Requires-Dist: faiss-cpu==1.12.0
Requires-Dist: setuptools==80.9.0
Requires-Dist: wheel==0.45.1
Requires-Dist: twine==6.2.0
Requires-Dist: pytest==8.4.2
Requires-Dist: chromadb==1.1.1
Provides-Extra: test
Requires-Dist: pytest==8.4.2; extra == "test"
Requires-Dist: pytest-cov==7.0.0; extra == "test"
Dynamic: license-file
